etcd3/__init__.py
etcd3/client.py
etcd3/events.py
etcd3/exceptions.py
etcd3/leases.py
etcd3/locks.py
etcd3/members.py
etcd3/transactions.py
etcd3/utils.py
etcd3/watch.py
etcd3/etcdrpc/__init__.py
etcd3/etcdrpc/auth_pb2.py
etcd3/etcdrpc/kv_pb2.py
etcd3/etcdrpc/rpc_pb2.py
etcd3/etcdrpc/rpc_pb2_grpc.py
zencore_etcd3-0.12.0.20220817.dist-info/AUTHORS.rst
zencore_etcd3-0.12.0.20220817.dist-info/LICENSE
zencore_etcd3-0.12.0.20220817.dist-info/METADATA
zencore_etcd3-0.12.0.20220817.dist-info/WHEEL
zencore_etcd3-0.12.0.20220817.dist-info/top_level.txt
zencore_etcd3-0.12.0.20220817.dist-info/RECORD
